pipfile2req/__init__.py
pipfile2req/__main__.py
pipfile2req/requirements.py
pipfile_requirements-0.3.0.dist-info/LICENSE
pipfile_requirements-0.3.0.dist-info/METADATA
pipfile_requirements-0.3.0.dist-info/WHEEL
pipfile_requirements-0.3.0.dist-info/entry_points.txt
pipfile_requirements-0.3.0.dist-info/top_level.txt
pipfile_requirements-0.3.0.dist-info/RECORD
