Metadata-Version: 2.1
Name: pipfile-requirements
Version: 0.3.0
Summary: A CLI tool to covert Pipfile/Pipfile.lock to requirments.txt
Home-page: https://github.com/frostming/pipfile-requirements
Author: Frost Ming
Author-email: mianghong@gmail.com
License: MIT
Platform: UNKNOWN
Classifier: Development Status :: 3 - Alpha
Classifier: License :: OSI Approved :: MIT License
Classifier: Programming Language :: Python
Classifier: Programming Language :: Python :: 2
Classifier: Programming Language :: Python :: 2.7
Classifier: Programming Language :: Python :: 3
Classifier: Programming Language :: Python :: 3.4
Classifier: Programming Language :: Python :: 3.5
Classifier: Programming Language :: Python :: 3.6
Classifier: Programming Language :: Python :: 3.7
Requires-Dist: toml
Requires-Dist: packaging
